Metadata-Version: 1.2
Name: lince
Version: 0.0.1a0
Summary: Configuration engine
Home-page: https://github.com/txomon/lince
Author: Javier Domingo Cansino
Author-email: javierdo1@gmail.com
License: UNKNOWN
Keywords: configuration,config,dynamic,file,json,environment,variable
Platform: UNKNOWN
Classifier: Development Status :: 1 - Planning
Classifier: Intended Audience :: Developers
Classifier: Topic :: Software Development :: Libraries
Classifier: License :: OSI Approved :: MIT License
Classifier: Programming Language :: Python :: 3.6
Requires-Python: >=3.6
